champions/__init__.py
champions/cli.py
champions/model/__init__.py
champions/model/champions.py
champions/model/datacard.py
champions/model/dataframes.py
champions/model/filter.py
champions/model/settings.py
champions/service/__init__.py
champions/service/darkwing.py
champions/service/datacardhelper.py
champions/service/eval.py
champions/service/train.py
champions-0.12.0.dist-info/METADATA
champions-0.12.0.dist-info/WHEEL
champions-0.12.0.dist-info/entry_points.txt
champions-0.12.0.dist-info/licenses/LICENSE
champions-0.12.0.dist-info/RECORD
