Metadata-Version: 2.4
Name: champions
Version: 0.12.0
Summary: Add your description here
Project-URL: Homepage, https://champions-ab0723.gitlab.io
Project-URL: Repository, https://gitlab.com/gwhe/champions
Project-URL: Issues, https://gitlab.com/gwhe/champions/-/issues
Author-email: swayand <stefan.wayand@gmail.com>
License-Expression: GPL-3.0-or-later
License-File: LICENSE
Classifier: Operating System :: OS Independent
Classifier: Programming Language :: Python :: 3
Requires-Python: >=3.13
Requires-Dist: altair>=5.5.0
Requires-Dist: duckdb>=1.4.1
Requires-Dist: mi-amore>=0.1.3
Requires-Dist: polars>=1.35.2
Requires-Dist: pyarrow>=19.0.1
Requires-Dist: pydantic>=2.10.6
Requires-Dist: pyyaml>=6.0.2
Requires-Dist: sympy>=1.14.0
Requires-Dist: typer>=0.15.2
Requires-Dist: vl-convert-python>=1.8.0
